<annotation>
    <folder>images_subset</folder>
    <filename>42.6953983_2.7688317.png</filename>
    <path>/Users/rurikoimai/Documents/GitHub/Satellite_Pool_Detection/images_subset/42.6953983_2.7688317.png</path>
    <source>
        <database>Unknown</database>
    </source>
    <size>
        <width>512</width>
        <height>512</height>
        <depth>3</depth>
    </size>
    <segmented>0</segmented>
    <object>
        <name>pool</name>
        <pose>Unspecified</pose>
        <truncated>0</truncated>
        <difficult>0</difficult>
        <bndbox>
            <xmin>225.96866392325967</xmin>
            <ymin>207.13300863901932</ymin>
            <xmax>283.87917075153666</xmax>
            <ymax>278.22194947066765</ymax>
        </bndbox>
    </object>
</annotation>
