<annotation>
    <folder>images_subset</folder>
    <filename>42.7207459_2.9293501.png</filename>
    <path>/Users/rurikoimai/Documents/GitHub/Satellite_Pool_Detection/images_subset/42.7207459_2.9293501.png</path>
    <source>
        <database>Unknown</database>
    </source>
    <size>
        <width>512</width>
        <height>512</height>
        <depth>3</depth>
    </size>
    <segmented>0</segmented>
    <object>
        <name>pool</name>
        <pose>Unspecified</pose>
        <truncated>0</truncated>
        <difficult>0</difficult>
        <bndbox>
            <xmin>230.39193239906382</xmin>
            <ymin>285.7632208606804</ymin>
            <xmax>281.6711497836374</xmax>
            <ymax>198.2967217729187</ymax>
        </bndbox>
    </object>
</annotation>
