<annotation>
    <folder>images_subset</folder>
    <filename>43.1070664_-0.0724096.png</filename>
    <path>/Users/rurikoimai/Documents/GitHub/Satellite_Pool_Detection/images_subset/43.1070664_-0.0724096.png</path>
    <source>
        <database>Unknown</database>
    </source>
    <size>
        <width>512</width>
        <height>512</height>
        <depth>3</depth>
    </size>
    <segmented>0</segmented>
    <object>
        <name>pool</name>
        <pose>Unspecified</pose>
        <truncated>0</truncated>
        <difficult>0</difficult>
        <bndbox>
            <xmin>196.92316288043745</xmin>
            <ymin>258.6253354316639</ymin>
            <xmax>316.2751880579723</xmax>
            <ymax>224.09375764058032</ymax>
        </bndbox>
    </object>
</annotation>
