<annotation>
    <folder>images_subset</folder>
    <filename>43.5502545_1.5159741.png</filename>
    <path>/Users/rurikoimai/Documents/GitHub/Satellite_Pool_Detection/images_subset/43.5502545_1.5159741.png</path>
    <source>
        <database>Unknown</database>
    </source>
    <size>
        <width>512</width>
        <height>512</height>
        <depth>3</depth>
    </size>
    <segmented>0</segmented>
    <object>
        <name>pool</name>
        <pose>Unspecified</pose>
        <truncated>0</truncated>
        <difficult>0</difficult>
        <bndbox>
            <xmin>214.38018607945037</xmin>
            <ymin>244.06936325452517</ymin>
            <xmax>303.8544872850048</xmax>
            <ymax>233.87908712872837</ymax>
        </bndbox>
    </object>
</annotation>
