<annotation>
    <folder>images_subset</folder>
    <filename>43.5496284_1.5413863.png</filename>
    <path>/Users/rurikoimai/Documents/GitHub/Satellite_Pool_Detection/images_subset/43.5496284_1.5413863.png</path>
    <source>
        <database>Unknown</database>
    </source>
    <size>
        <width>512</width>
        <height>512</height>
        <depth>3</depth>
    </size>
    <segmented>0</segmented>
    <object>
        <name>pool</name>
        <pose>Unspecified</pose>
        <truncated>0</truncated>
        <difficult>0</difficult>
        <bndbox>
            <xmin>216.63031469914716</xmin>
            <ymin>222.1345220522627</ymin>
            <xmax>295.8185313693003</xmax>
            <ymax>259.53177343212195</ymax>
        </bndbox>
    </object>
</annotation>
