<annotation>
    <folder>images_subset</folder>
    <filename>43.5736713_1.3238962.png</filename>
    <path>/Users/rurikoimai/Documents/GitHub/Satellite_Pool_Detection/images_subset/43.5736713_1.3238962.png</path>
    <source>
        <database>Unknown</database>
    </source>
    <size>
        <width>512</width>
        <height>512</height>
        <depth>3</depth>
    </size>
    <segmented>0</segmented>
    <object>
        <name>pool</name>
        <pose>Unspecified</pose>
        <truncated>0</truncated>
        <difficult>0</difficult>
        <bndbox>
            <xmin>213.3730205071227</xmin>
            <ymin>205.93314058228702</ymin>
            <xmax>298.25188044695693</xmax>
            <ymax>278.17035839785626</ymax>
        </bndbox>
    </object>
</annotation>
