<annotation>
    <folder>images_subset</folder>
    <filename>43.5587904_1.5146363.png</filename>
    <path>/Users/rurikoimai/Documents/GitHub/Satellite_Pool_Detection/images_subset/43.5587904_1.5146363.png</path>
    <source>
        <database>Unknown</database>
    </source>
    <size>
        <width>512</width>
        <height>512</height>
        <depth>3</depth>
    </size>
    <segmented>0</segmented>
    <object>
        <name>pool</name>
        <pose>Unspecified</pose>
        <truncated>0</truncated>
        <difficult>0</difficult>
        <bndbox>
            <xmin>230.3596415572316</xmin>
            <ymin>272.57470954428965</ymin>
            <xmax>281.4936707901306</xmax>
            <ymax>211.40986349459223</ymax>
        </bndbox>
    </object>
</annotation>
