<annotation>
    <folder>images_subset</folder>
    <filename>43.6919302_1.520418.png</filename>
    <path>/Users/rurikoimai/Documents/GitHub/Satellite_Pool_Detection/images_subset/43.6919302_1.520418.png</path>
    <source>
        <database>Unknown</database>
    </source>
    <size>
        <width>512</width>
        <height>512</height>
        <depth>3</depth>
    </size>
    <segmented>0</segmented>
    <object>
        <name>pool</name>
        <pose>Unspecified</pose>
        <truncated>0</truncated>
        <difficult>0</difficult>
        <bndbox>
            <xmin>210.13080291364753</xmin>
            <ymin>226.55931358237373</ymin>
            <xmax>301.9443646395608</xmax>
            <ymax>257.336696933164</ymax>
        </bndbox>
    </object>
</annotation>
