<annotation>
    <folder>images_subset</folder>
    <filename>43.6212896_1.4527271.png</filename>
    <path>/Users/rurikoimai/Documents/GitHub/Satellite_Pool_Detection/images_subset/43.6212896_1.4527271.png</path>
    <source>
        <database>Unknown</database>
    </source>
    <size>
        <width>512</width>
        <height>512</height>
        <depth>3</depth>
    </size>
    <segmented>0</segmented>
    <object>
        <name>pool</name>
        <pose>Unspecified</pose>
        <truncated>0</truncated>
        <difficult>0</difficult>
        <bndbox>
            <xmin>223.3442508766775</xmin>
            <ymin>231.2640095104086</ymin>
            <xmax>292.14112407514995</xmax>
            <ymax>249.2702096785894</ymax>
        </bndbox>
    </object>
</annotation>
