<annotation>
    <folder>images_subset</folder>
    <filename>43.6391269_1.474232.png</filename>
    <path>/Users/rurikoimai/Documents/GitHub/Satellite_Pool_Detection/images_subset/43.6391269_1.474232.png</path>
    <source>
        <database>Unknown</database>
    </source>
    <size>
        <width>512</width>
        <height>512</height>
        <depth>3</depth>
    </size>
    <segmented>0</segmented>
    <object>
        <name>pool</name>
        <pose>Unspecified</pose>
        <truncated>0</truncated>
        <difficult>0</difficult>
        <bndbox>
            <xmin>206.06055459296292</xmin>
            <ymin>252.20850223329816</ymin>
            <xmax>305.93944540703706</xmax>
            <ymax>231.89523631079695</ymax>
        </bndbox>
    </object>
</annotation>
