<annotation>
    <folder>images_subset</folder>
    <filename>44.7441432_-1.0885518.png</filename>
    <path>/Users/rurikoimai/Documents/GitHub/Satellite_Pool_Detection/images_subset/44.7441432_-1.0885518.png</path>
    <source>
        <database>Unknown</database>
    </source>
    <size>
        <width>512</width>
        <height>512</height>
        <depth>3</depth>
    </size>
    <segmented>0</segmented>
    <object>
        <name>pool</name>
        <pose>Unspecified</pose>
        <truncated>0</truncated>
        <difficult>0</difficult>
        <bndbox>
            <xmin>196.33167858972615</xmin>
            <ymin>235.009278835948</ymin>
            <xmax>315.6812979471341</xmax>
            <ymax>234.68322773949333</ymax>
        </bndbox>
    </object>
</annotation>
